<root>
    <item name='com.sun.org.apache.xerces.internal.util.AugmentationsImpl.LargeContainer com.sun.org.apache.xerces.internal.util.AugmentationsImpl.AugmentationsItemsContainer expand()'>
        <annotation name='org.jetbrains.annotations.NotNull'/>
    </item>
    <item name='com.sun.org.apache.xerces.internal.util.AugmentationsImpl.LargeContainer fAugmentations'>
        <annotation name='org.jetbrains.annotations.NotNull'/>
    </item>
    <item name='com.sun.org.apache.xerces.internal.util.AugmentationsImpl.LargeContainer java.lang.String toString()'>
        <annotation name='org.jetbrains.annotations.NotNull'/>
    </item>
    <item name='com.sun.org.apache.xerces.internal.util.AugmentationsImpl.SmallContainer.SmallContainerKeyEnumeration this$1'>
        <annotation name='org.jetbrains.annotations.NotNull'/>
    </item>
    <item name='com.sun.org.apache.xerces.internal.util.AugmentationsImpl.SmallContainer com.sun.org.apache.xerces.internal.util.AugmentationsImpl.AugmentationsItemsContainer expand()'>
        <annotation name='org.jetbrains.annotations.NotNull'/>
    </item>
    <item name='com.sun.org.apache.xerces.internal.util.AugmentationsImpl.SmallContainer fAugmentations'>
        <annotation name='org.jetbrains.annotations.NotNull'/>
    </item>
    <item name='com.sun.org.apache.xerces.internal.util.AugmentationsImpl.SmallContainer java.util.Enumeration keys()'>
        <annotation name='org.jetbrains.annotations.NotNull'/>
    </item>
    <item name='com.sun.org.apache.xerces.internal.util.AugmentationsImpl.SmallContainer java.lang.String toString()'>
        <annotation name='org.jetbrains.annotations.NotNull'/>
    </item>
    <item name='com.sun.org.apache.xerces.internal.util.AugmentationsImpl java.lang.String toString()'>
        <annotation name='org.jetbrains.annotations.NotNull'/>
    </item>
    <item name='com.sun.org.apache.xerces.internal.util.DOMEntityResolverWrapper XML_TYPE'>
        <annotation name='org.jetbrains.annotations.NotNull'/>
    </item>
    <item name='com.sun.org.apache.xerces.internal.util.DOMEntityResolverWrapper XSD_TYPE'>
        <annotation name='org.jetbrains.annotations.NotNull'/>
    </item>
    <item name='com.sun.org.apache.xerces.internal.util.DOMEntityResolverWrapper java.lang.String getType(com.sun.org.apache.xerces.internal.xni.XMLResourceIdentifier)'>
        <annotation name='org.jetbrains.annotations.NotNull'/>
    </item>
    <item name='com.sun.org.apache.xerces.internal.util.DOMErrorHandlerWrapper fDOMError'>
        <annotation name='org.jetbrains.annotations.NotNull'/>
    </item>
    <item name='com.sun.org.apache.xerces.internal.util.DOMErrorHandlerWrapper fErrorCode'>
        <annotation name='org.jetbrains.annotations.NotNull'/>
    </item>
    <item name='com.sun.org.apache.xerces.internal.util.DOMUtil org.w3c.dom.DOMException createDOMException(short, java.lang.Throwable)'>
        <annotation name='org.jetbrains.annotations.NotNull'/>
    </item>
    <item name='com.sun.org.apache.xerces.internal.util.DOMUtil org.w3c.dom.ls.LSException createLSException(short, java.lang.Throwable)'>
        <annotation name='org.jetbrains.annotations.NotNull'/>
    </item>
    <item name='com.sun.org.apache.xerces.internal.util.DOMUtil org.w3c.dom.Attr[] getAttrs(org.w3c.dom.Element)'>
        <annotation name='org.jetbrains.annotations.NotNull'/>
    </item>
    <item name='com.sun.org.apache.xerces.internal.util.DatatypeMessageFormatter BASE_NAME'>
        <annotation name='org.jetbrains.annotations.NotNull'/>
    </item>
    <item name='com.sun.org.apache.xerces.internal.util.DraconianErrorHandler theInstance'>
        <annotation name='org.jetbrains.annotations.NotNull'/>
    </item>
    <item name='com.sun.org.apache.xerces.internal.util.EncodingMap fIANA2JavaMap'>
        <annotation name='org.jetbrains.annotations.NotNull'/>
    </item>
    <item name='com.sun.org.apache.xerces.internal.util.EncodingMap fJava2IANAMap'>
        <annotation name='org.jetbrains.annotations.NotNull'/>
    </item>
    <item name='com.sun.org.apache.xerces.internal.util.EntityResolver2Wrapper com.sun.org.apache.xerces.internal.xni.parser.XMLInputSource createXMLInputSource(org.xml.sax.InputSource, java.lang.String)'>
        <annotation name='org.jetbrains.annotations.NotNull'/>
    </item>
    <item name='com.sun.org.apache.xerces.internal.util.ErrorHandlerWrapper org.xml.sax.SAXParseException createSAXParseException(com.sun.org.apache.xerces.internal.xni.parser.XMLParseException)'>
        <annotation name='org.jetbrains.annotations.NotNull'/>
    </item>
    <item name='com.sun.org.apache.xerces.internal.util.ErrorHandlerWrapper com.sun.org.apache.xerces.internal.xni.parser.XMLParseException createXMLParseException(org.xml.sax.SAXParseException)'>
        <annotation name='org.jetbrains.annotations.NotNull'/>
    </item>
    <item name='com.sun.org.apache.xerces.internal.util.ErrorHandlerWrapper com.sun.org.apache.xerces.internal.xni.XNIException createXNIException(org.xml.sax.SAXException)'>
        <annotation name='org.jetbrains.annotations.NotNull'/>
    </item>
    <item name='com.sun.org.apache.xerces.internal.util.FeatureState NOT_ALLOWED'>
        <annotation name='org.jetbrains.annotations.NotNull'/>
    </item>
    <item name='com.sun.org.apache.xerces.internal.util.FeatureState NOT_RECOGNIZED'>
        <annotation name='org.jetbrains.annotations.NotNull'/>
    </item>
    <item name='com.sun.org.apache.xerces.internal.util.FeatureState NOT_SUPPORTED'>
        <annotation name='org.jetbrains.annotations.NotNull'/>
    </item>
    <item name='com.sun.org.apache.xerces.internal.util.FeatureState RECOGNIZED'>
        <annotation name='org.jetbrains.annotations.NotNull'/>
    </item>
    <item name='com.sun.org.apache.xerces.internal.util.FeatureState SET_DISABLED'>
        <annotation name='org.jetbrains.annotations.NotNull'/>
    </item>
    <item name='com.sun.org.apache.xerces.internal.util.FeatureState SET_ENABLED'>
        <annotation name='org.jetbrains.annotations.NotNull'/>
    </item>
    <item name='com.sun.org.apache.xerces.internal.util.FeatureState UNKNOWN'>
        <annotation name='org.jetbrains.annotations.NotNull'/>
    </item>
    <item name='com.sun.org.apache.xerces.internal.util.FeatureState com.sun.org.apache.xerces.internal.util.FeatureState is(boolean)'>
        <annotation name='org.jetbrains.annotations.NotNull'/>
    </item>
    <item name='com.sun.org.apache.xerces.internal.util.FeatureState com.sun.org.apache.xerces.internal.util.FeatureState of(com.sun.org.apache.xerces.internal.util.Status)'>
        <annotation name='org.jetbrains.annotations.NotNull'/>
    </item>
    <item name='com.sun.org.apache.xerces.internal.util.JAXPNamespaceContextWrapper fAllPrefixes'>
        <annotation name='org.jetbrains.annotations.NotNull'/>
    </item>
    <item name='com.sun.org.apache.xerces.internal.util.JAXPNamespaceContextWrapper java.util.Enumeration getAllPrefixes()'>
        <annotation name='org.jetbrains.annotations.NotNull'/>
    </item>
    <item name='com.sun.org.apache.xerces.internal.util.NamespaceContextWrapper java.util.Iterator getPrefixes(java.lang.String)'>
        <annotation name='org.jetbrains.annotations.NotNull'/>
    </item>
    <item name='com.sun.org.apache.xerces.internal.util.NamespaceSupport.IteratorPrefixes java.lang.String toString()'>
        <annotation name='org.jetbrains.annotations.NotNull'/>
    </item>
    <item name='com.sun.org.apache.xerces.internal.util.NamespaceSupport.Prefixes java.lang.String toString()'>
        <annotation name='org.jetbrains.annotations.NotNull'/>
    </item>
    <item name='com.sun.org.apache.xerces.internal.util.NamespaceSupport java.util.Enumeration getAllPrefixes()'>
        <annotation name='org.jetbrains.annotations.NotNull'/>
    </item>
    <item name='com.sun.org.apache.xerces.internal.util.NamespaceSupport java.util.Iterator getPrefixes()'>
        <annotation name='org.jetbrains.annotations.NotNull'/>
    </item>
    <item name='com.sun.org.apache.xerces.internal.util.NamespaceSupport java.util.Vector getPrefixes(java.lang.String)'>
        <annotation name='org.jetbrains.annotations.NotNull'/>
    </item>
    <item name='com.sun.org.apache.xerces.internal.util.ParserConfigurationSettings PARSER_SETTINGS'>
        <annotation name='org.jetbrains.annotations.NotNull'/>
    </item>
    <item name='com.sun.org.apache.xerces.internal.util.ParserConfigurationSettings com.sun.org.apache.xerces.internal.util.FeatureState getFeatureState(java.lang.String)'>
        <annotation name='org.jetbrains.annotations.NotNull'/>
    </item>
    <item name='com.sun.org.apache.xerces.internal.util.ParserConfigurationSettings com.sun.org.apache.xerces.internal.util.PropertyState getPropertyState(java.lang.String)'>
        <annotation name='org.jetbrains.annotations.NotNull'/>
    </item>
    <item name='com.sun.org.apache.xerces.internal.util.PropertyState NOT_ALLOWED'>
        <annotation name='org.jetbrains.annotations.NotNull'/>
    </item>
    <item name='com.sun.org.apache.xerces.internal.util.PropertyState NOT_RECOGNIZED'>
        <annotation name='org.jetbrains.annotations.NotNull'/>
    </item>
    <item name='com.sun.org.apache.xerces.internal.util.PropertyState NOT_SUPPORTED'>
        <annotation name='org.jetbrains.annotations.NotNull'/>
    </item>
    <item name='com.sun.org.apache.xerces.internal.util.PropertyState RECOGNIZED'>
        <annotation name='org.jetbrains.annotations.NotNull'/>
    </item>
    <item name='com.sun.org.apache.xerces.internal.util.PropertyState UNKNOWN'>
        <annotation name='org.jetbrains.annotations.NotNull'/>
    </item>
    <item name='com.sun.org.apache.xerces.internal.util.PropertyState com.sun.org.apache.xerces.internal.util.PropertyState is(java.lang.Object)'>
        <annotation name='org.jetbrains.annotations.NotNull'/>
    </item>
    <item name='com.sun.org.apache.xerces.internal.util.PropertyState com.sun.org.apache.xerces.internal.util.PropertyState of(com.sun.org.apache.xerces.internal.util.Status)'>
        <annotation name='org.jetbrains.annotations.NotNull'/>
    </item>
    <item name='com.sun.org.apache.xerces.internal.util.SAX2XNI com.sun.org.apache.xerces.internal.xni.XMLAttributes createAttributes(org.xml.sax.Attributes)'>
        <annotation name='org.jetbrains.annotations.NotNull'/>
    </item>
    <item name='com.sun.org.apache.xerces.internal.util.SAX2XNI com.sun.org.apache.xerces.internal.xni.QName createQName(java.lang.String, java.lang.String, java.lang.String)'>
        <annotation name='org.jetbrains.annotations.NotNull'/>
    </item>
    <item name='com.sun.org.apache.xerces.internal.util.SAX2XNI com.sun.org.apache.xerces.internal.xni.XMLString createXMLString(java.lang.String)'>
        <annotation name='org.jetbrains.annotations.NotNull'/>
    </item>
    <item name='com.sun.org.apache.xerces.internal.util.SAX2XNI nsContext'>
        <annotation name='org.jetbrains.annotations.NotNull'/>
    </item>
    <item name='com.sun.org.apache.xerces.internal.util.SAX2XNI symbolTable'>
        <annotation name='org.jetbrains.annotations.NotNull'/>
    </item>
    <item name='com.sun.org.apache.xerces.internal.util.SAX2XNI xa'>
        <annotation name='org.jetbrains.annotations.NotNull'/>
    </item>
    <item name='com.sun.org.apache.xerces.internal.util.Status $VALUES'>
        <annotation name='org.jetbrains.annotations.NotNull'/>
    </item>
    <item name='com.sun.org.apache.xerces.internal.util.Status NOT_ALLOWED'>
        <annotation name='org.jetbrains.annotations.NotNull'/>
    </item>
    <item name='com.sun.org.apache.xerces.internal.util.Status NOT_RECOGNIZED'>
        <annotation name='org.jetbrains.annotations.NotNull'/>
    </item>
    <item name='com.sun.org.apache.xerces.internal.util.Status NOT_SUPPORTED'>
        <annotation name='org.jetbrains.annotations.NotNull'/>
    </item>
    <item name='com.sun.org.apache.xerces.internal.util.Status RECOGNIZED'>
        <annotation name='org.jetbrains.annotations.NotNull'/>
    </item>
    <item name='com.sun.org.apache.xerces.internal.util.Status SET'>
        <annotation name='org.jetbrains.annotations.NotNull'/>
    </item>
    <item name='com.sun.org.apache.xerces.internal.util.Status UNKNOWN'>
        <annotation name='org.jetbrains.annotations.NotNull'/>
    </item>
    <item name='com.sun.org.apache.xerces.internal.util.Status com.sun.org.apache.xerces.internal.util.Status valueOf(java.lang.String)'>
        <annotation name='org.jetbrains.annotations.NotNull'/>
    </item>
    <item name='com.sun.org.apache.xerces.internal.util.SymbolHash.Entry com.sun.org.apache.xerces.internal.util.SymbolHash.Entry makeClone()'>
        <annotation name='org.jetbrains.annotations.NotNull'/>
    </item>
    <item name='com.sun.org.apache.xerces.internal.util.SymbolHash java.lang.Object[] getEntries()'>
        <annotation name='org.jetbrains.annotations.NotNull'/>
    </item>
    <item name='com.sun.org.apache.xerces.internal.util.SymbolHash com.sun.org.apache.xerces.internal.util.SymbolHash makeClone()'>
        <annotation name='org.jetbrains.annotations.NotNull'/>
    </item>
    <item name='com.sun.org.apache.xerces.internal.util.TypeInfoImpl dtdCache'>
        <annotation name='org.jetbrains.annotations.NotNull'/>
    </item>
    <item name='com.sun.org.apache.xerces.internal.util.TypeInfoImpl dtdNamespaceURI'>
        <annotation name='org.jetbrains.annotations.NotNull'/>
    </item>
    <item name='com.sun.org.apache.xerces.internal.util.TypeInfoImpl org.w3c.dom.TypeInfo getDTDTypeInfo(java.lang.String)'>
        <annotation name='org.jetbrains.annotations.NotNull'/>
    </item>
    <item name='com.sun.org.apache.xerces.internal.util.URI fgLookupTable'>
        <annotation name='org.jetbrains.annotations.NotNull'/>
    </item>
    <item name='com.sun.org.apache.xerces.internal.util.URI java.lang.String getAuthority()'>
        <annotation name='org.jetbrains.annotations.NotNull'/>
    </item>
    <item name='com.sun.org.apache.xerces.internal.util.URI java.lang.String getPath(boolean, boolean)'>
        <annotation name='org.jetbrains.annotations.NotNull'/>
    </item>
    <item name='com.sun.org.apache.xerces.internal.util.URI java.lang.String getSchemeSpecificPart()'>
        <annotation name='org.jetbrains.annotations.NotNull'/>
    </item>
    <item name='com.sun.org.apache.xerces.internal.util.URI java.lang.String toString()'>
        <annotation name='org.jetbrains.annotations.NotNull'/>
    </item>
    <item name='com.sun.org.apache.xerces.internal.util.XML11Char XML11CHARS'>
        <annotation name='org.jetbrains.annotations.NotNull'/>
    </item>
    <item name='com.sun.org.apache.xerces.internal.util.XMLAttributesImpl java.lang.String getReportableType(java.lang.String)'>
        <annotation name='org.jetbrains.annotations.NotNull'/>
    </item>
    <item name='com.sun.org.apache.xerces.internal.util.XMLChar CHARS'>
        <annotation name='org.jetbrains.annotations.NotNull'/>
    </item>
    <item name='com.sun.org.apache.xerces.internal.util.XMLChar java.lang.String trim(java.lang.String)'>
        <annotation name='org.jetbrains.annotations.NotNull'/>
    </item>
    <item name='com.sun.org.apache.xerces.internal.util.XMLEntityDescriptionImpl java.lang.String toString()'>
        <annotation name='org.jetbrains.annotations.NotNull'/>
    </item>
    <item name='com.sun.org.apache.xerces.internal.util.XMLGrammarPoolImpl com.sun.org.apache.xerces.internal.xni.grammars.Grammar[] retrieveInitialGrammarSet(java.lang.String)'>
        <annotation name='org.jetbrains.annotations.NotNull'/>
    </item>
    <item name='com.sun.org.apache.xerces.internal.util.XMLResourceIdentifierImpl java.lang.String toString()'>
        <annotation name='org.jetbrains.annotations.NotNull'/>
    </item>
</root>
