<root>
    <item name='com.sun.corba.se.impl.encoding.BufferManagerFactory com.sun.corba.se.impl.encoding.BufferManagerRead defaultBufferManagerRead(com.sun.corba.se.spi.orb.ORB)'>
        <annotation name='org.jetbrains.annotations.NotNull'/>
    </item>
    <item name='com.sun.corba.se.impl.encoding.BufferManagerFactory com.sun.corba.se.impl.encoding.BufferManagerRead newBufferManagerRead(int, byte, com.sun.corba.se.spi.orb.ORB)'>
        <annotation name='org.jetbrains.annotations.NotNull'/>
    </item>
    <item name='com.sun.corba.se.impl.encoding.BufferManagerFactory com.sun.corba.se.impl.encoding.BufferManagerRead newBufferManagerRead(com.sun.corba.se.spi.ior.iiop.GIOPVersion, byte, com.sun.corba.se.spi.orb.ORB)'>
        <annotation name='org.jetbrains.annotations.NotNull'/>
    </item>
    <item name='com.sun.corba.se.impl.encoding.BufferManagerFactory com.sun.corba.se.impl.encoding.BufferManagerWrite newBufferManagerWrite(int, byte, com.sun.corba.se.spi.orb.ORB)'>
        <annotation name='org.jetbrains.annotations.NotNull'/>
    </item>
    <item name='com.sun.corba.se.impl.encoding.BufferManagerFactory com.sun.corba.se.impl.encoding.BufferManagerWrite newBufferManagerWrite(com.sun.corba.se.spi.ior.iiop.GIOPVersion, byte, com.sun.corba.se.spi.orb.ORB)'>
        <annotation name='org.jetbrains.annotations.NotNull'/>
    </item>
    <item name='com.sun.corba.se.impl.encoding.BufferManagerReadGrow com.sun.corba.se.impl.encoding.MarkAndResetHandler getMarkAndResetHandler()'>
        <annotation name='org.jetbrains.annotations.NotNull'/>
    </item>
    <item name='com.sun.corba.se.impl.encoding.BufferManagerReadStream com.sun.corba.se.impl.encoding.MarkAndResetHandler getMarkAndResetHandler()'>
        <annotation name='org.jetbrains.annotations.NotNull'/>
    </item>
    <item name='com.sun.corba.se.impl.encoding.BufferManagerReadStream com.sun.corba.se.impl.encoding.ByteBufferWithInfo underflow(com.sun.corba.se.impl.encoding.ByteBufferWithInfo)'>
        <annotation name='org.jetbrains.annotations.NotNull'/>
    </item>
    <item name='com.sun.corba.se.impl.encoding.BufferManagerWriteCollect java.util.Iterator iterator()'>
        <annotation name='org.jetbrains.annotations.NotNull'/>
    </item>
    <item name='com.sun.corba.se.impl.encoding.ByteBufferWithInfo java.lang.String toString()'>
        <annotation name='org.jetbrains.annotations.NotNull'/>
    </item>
    <item name='com.sun.corba.se.impl.encoding.CDRInputObject com.sun.corba.se.impl.encoding.CodeSetConversion.BTCConverter createCharBTCConverter()'>
        <annotation name='org.jetbrains.annotations.NotNull'/>
    </item>
    <item name='com.sun.corba.se.impl.encoding.CDRInputObject com.sun.corba.se.impl.encoding.CodeSetConversion.BTCConverter createWCharBTCConverter()'>
        <annotation name='org.jetbrains.annotations.NotNull'/>
    </item>
    <item name='com.sun.corba.se.impl.encoding.CDRInputStream.InputStreamFactory com.sun.corba.se.impl.encoding.CDRInputStreamBase newInputStream(com.sun.corba.se.spi.orb.ORB, com.sun.corba.se.spi.ior.iiop.GIOPVersion, byte)'>
        <annotation name='org.jetbrains.annotations.NotNull'/>
    </item>
    <item name='com.sun.corba.se.impl.encoding.CDRInputStream com.sun.corba.se.impl.encoding.CodeSetConversion.BTCConverter createCharBTCConverter()'>
        <annotation name='org.jetbrains.annotations.NotNull'/>
    </item>
    <item name='com.sun.corba.se.impl.encoding.CDRInputStream_1_0.1 java.lang.Object run()'>
        <annotation name='org.jetbrains.annotations.NotNull'/>
    </item>
    <item name='com.sun.corba.se.impl.encoding.CDRInputStream_1_0.StreamMemento this$0'>
        <annotation name='org.jetbrains.annotations.NotNull'/>
    </item>
    <item name='com.sun.corba.se.impl.encoding.CDRInputStream_1_0 _id'>
        <annotation name='org.jetbrains.annotations.NotNull'/>
    </item>
    <item name='com.sun.corba.se.impl.encoding.CDRInputStream_1_0 _ids'>
        <annotation name='org.jetbrains.annotations.NotNull'/>
    </item>
    <item name='com.sun.corba.se.impl.encoding.CDRInputStream_1_0 java.lang.Object createStreamMemento()'>
        <annotation name='org.jetbrains.annotations.NotNull'/>
    </item>
    <item name='com.sun.corba.se.impl.encoding.CDRInputStream_1_0 com.sun.corba.se.impl.encoding.CDRInputStreamBase dup()'>
        <annotation name='org.jetbrains.annotations.NotNull'/>
    </item>
    <item name='com.sun.corba.se.impl.encoding.CDRInputStream_1_0 org.omg.CORBA.Object internalIORToObject(com.sun.corba.se.spi.ior.IOR, com.sun.corba.se.spi.presentation.rmi.PresentationManager.StubFactory, com.sun.corba.se.spi.orb.ORB)'>
        <annotation name='org.jetbrains.annotations.NotNull'/>
    </item>
    <item name='com.sun.corba.se.impl.encoding.CDRInputStream_1_0 java.lang.String internalReadString(int)'>
        <annotation name='org.jetbrains.annotations.NotNull'/>
    </item>
    <item name='com.sun.corba.se.impl.encoding.CDRInputStream_1_0 kReadMethod'>
        <annotation name='org.jetbrains.annotations.NotNull'/>
    </item>
    <item name='com.sun.corba.se.impl.encoding.CDRInputStream_1_0 java.lang.String legacyReadString(int)'>
        <annotation name='org.jetbrains.annotations.NotNull'/>
    </item>
    <item name='com.sun.corba.se.impl.encoding.CDRInputStream_1_0 org.omg.CORBA.Principal read_Principal()'>
        <annotation name='org.jetbrains.annotations.NotNull'/>
    </item>
    <item name='com.sun.corba.se.impl.encoding.CDRInputStream_1_0 org.omg.CORBA.TypeCode read_TypeCode()'>
        <annotation name='org.jetbrains.annotations.NotNull'/>
    </item>
    <item name='com.sun.corba.se.impl.encoding.CDRInputStream_1_0 org.omg.CORBA.Any read_any()'>
        <annotation name='org.jetbrains.annotations.NotNull'/>
    </item>
    <item name='com.sun.corba.se.impl.encoding.CDRInputStream_1_0 java.math.BigDecimal read_fixed()'>
        <annotation name='org.jetbrains.annotations.NotNull'/>
    </item>
    <item name='com.sun.corba.se.impl.encoding.CDRInputStream_1_0 java.math.BigDecimal read_fixed(short, short)'>
        <annotation name='org.jetbrains.annotations.NotNull'/>
    </item>
    <item name='com.sun.corba.se.impl.encoding.CDRInputStream_1_0 java.lang.StringBuffer read_fixed_buffer()'>
        <annotation name='org.jetbrains.annotations.NotNull'/>
    </item>
    <item name='com.sun.corba.se.impl.encoding.CDRInputStream_1_0 java.lang.String read_wstring()'>
        <annotation name='org.jetbrains.annotations.NotNull'/>
    </item>
    <item name='com.sun.corba.se.impl.encoding.CDRInputStream_1_1.FragmentableStreamMemento this$0'>
        <annotation name='org.jetbrains.annotations.NotNull'/>
    </item>
    <item name='com.sun.corba.se.impl.encoding.CDRInputStream_1_1 java.lang.Object createStreamMemento()'>
        <annotation name='org.jetbrains.annotations.NotNull'/>
    </item>
    <item name='com.sun.corba.se.impl.encoding.CDRInputStream_1_1 com.sun.corba.se.impl.encoding.CDRInputStreamBase dup()'>
        <annotation name='org.jetbrains.annotations.NotNull'/>
    </item>
    <item name='com.sun.corba.se.impl.encoding.CDRInputStream_1_1 java.lang.String read_wstring()'>
        <annotation name='org.jetbrains.annotations.NotNull'/>
    </item>
    <item name='com.sun.corba.se.impl.encoding.CDRInputStream_1_2 com.sun.corba.se.impl.encoding.CDRInputStreamBase dup()'>
        <annotation name='org.jetbrains.annotations.NotNull'/>
    </item>
    <item name='com.sun.corba.se.impl.encoding.CDRInputStream_1_2 java.lang.String read_wstring()'>
        <annotation name='org.jetbrains.annotations.NotNull'/>
    </item>
    <item name='com.sun.corba.se.impl.encoding.CDROutputObject com.sun.corba.se.impl.encoding.CodeSetConversion.CTBConverter createWCharCTBConverter()'>
        <annotation name='org.jetbrains.annotations.NotNull'/>
    </item>
    <item name='com.sun.corba.se.impl.encoding.CDROutputStream.OutputStreamFactory com.sun.corba.se.impl.encoding.CDROutputStreamBase newOutputStream(com.sun.corba.se.spi.orb.ORB, com.sun.corba.se.spi.ior.iiop.GIOPVersion, byte)'>
        <annotation name='org.jetbrains.annotations.NotNull'/>
    </item>
    <item name='com.sun.corba.se.impl.encoding.CDROutputStream com.sun.corba.se.impl.encoding.CodeSetConversion.CTBConverter createCharCTBConverter()'>
        <annotation name='org.jetbrains.annotations.NotNull'/>
    </item>
    <item name='com.sun.corba.se.impl.encoding.CDROutputStream_1_0.1 java.lang.Object run()'>
        <annotation name='org.jetbrains.annotations.NotNull'/>
    </item>
    <item name='com.sun.corba.se.impl.encoding.CDROutputStream_1_0 _id'>
        <annotation name='org.jetbrains.annotations.NotNull'/>
    </item>
    <item name='com.sun.corba.se.impl.encoding.CDROutputStream_1_0 _ids'>
        <annotation name='org.jetbrains.annotations.NotNull'/>
    </item>
    <item name='com.sun.corba.se.impl.encoding.CDROutputStream_1_0 kWriteMethod'>
        <annotation name='org.jetbrains.annotations.NotNull'/>
    </item>
    <item name='com.sun.corba.se.impl.encoding.CDROutputStream_1_0 byte[] toByteArray()'>
        <annotation name='org.jetbrains.annotations.NotNull'/>
    </item>
    <item name='com.sun.corba.se.impl.encoding.CachedCodeBase org.omg.CORBA.Object getObjectFromIOR()'>
        <annotation name='org.jetbrains.annotations.NotNull'/>
    </item>
    <item name='com.sun.corba.se.impl.encoding.CachedCodeBase java.lang.String[] implementations(java.lang.String[])'>
        <annotation name='org.jetbrains.annotations.NotNull'/>
    </item>
    <item name='com.sun.corba.se.impl.encoding.CachedCodeBase com.sun.org.omg.CORBA.ValueDefPackage.FullValueDescription[] metas(java.lang.String[])'>
        <annotation name='org.jetbrains.annotations.NotNull'/>
    </item>
    <item name='com.sun.corba.se.impl.encoding.CodeSetCache.1 java.lang.Object initialValue()'>
        <annotation name='org.jetbrains.annotations.NotNull'/>
    </item>
    <item name='com.sun.corba.se.impl.encoding.CodeSetComponentInfo.CodeSetComponent java.lang.String toString()'>
        <annotation name='org.jetbrains.annotations.NotNull'/>
    </item>
    <item name='com.sun.corba.se.impl.encoding.CodeSetComponentInfo.CodeSetContext java.lang.String toString()'>
        <annotation name='org.jetbrains.annotations.NotNull'/>
    </item>
    <item name='com.sun.corba.se.impl.encoding.CodeSetComponentInfo JAVASOFT_DEFAULT_CODESETS'>
        <annotation name='org.jetbrains.annotations.NotNull'/>
    </item>
    <item name='com.sun.corba.se.impl.encoding.CodeSetComponentInfo LOCAL_CODE_SETS'>
        <annotation name='org.jetbrains.annotations.NotNull'/>
    </item>
    <item name='com.sun.corba.se.impl.encoding.CodeSetComponentInfo com.sun.corba.se.impl.encoding.CodeSetComponentInfo.CodeSetComponent createFromString(java.lang.String)'>
        <annotation name='org.jetbrains.annotations.NotNull'/>
    </item>
    <item name='com.sun.corba.se.impl.encoding.CodeSetComponentInfo java.lang.String toString()'>
        <annotation name='org.jetbrains.annotations.NotNull'/>
    </item>
    <item name='com.sun.corba.se.impl.encoding.CodeSetConversion.CodeSetConversionHolder csc'>
        <annotation name='org.jetbrains.annotations.NotNull'/>
    </item>
    <item name='com.sun.corba.se.impl.encoding.CodeSetConversion.JavaCTBConverter this$0'>
        <annotation name='org.jetbrains.annotations.NotNull'/>
    </item>
    <item name='com.sun.corba.se.impl.encoding.CodeSetConversion.UTF16CTBConverter this$0'>
        <annotation name='org.jetbrains.annotations.NotNull'/>
    </item>
    <item name='com.sun.corba.se.impl.encoding.CodeSetConversion com.sun.corba.se.impl.encoding.CodeSetConversion.BTCConverter getBTCConverter(com.sun.corba.se.impl.encoding.OSFCodeSetRegistry.Entry)'>
        <annotation name='org.jetbrains.annotations.NotNull'/>
    </item>
    <item name='com.sun.corba.se.impl.encoding.CodeSetConversion com.sun.corba.se.impl.encoding.CodeSetConversion.BTCConverter getBTCConverter(com.sun.corba.se.impl.encoding.OSFCodeSetRegistry.Entry, boolean)'>
        <annotation name='org.jetbrains.annotations.NotNull'/>
    </item>
    <item name='com.sun.corba.se.impl.encoding.CodeSetConversion com.sun.corba.se.impl.encoding.CodeSetConversion.CTBConverter getCTBConverter(com.sun.corba.se.impl.encoding.OSFCodeSetRegistry.Entry)'>
        <annotation name='org.jetbrains.annotations.NotNull'/>
    </item>
    <item name='com.sun.corba.se.impl.encoding.CodeSetConversion com.sun.corba.se.impl.encoding.CodeSetConversion.CTBConverter getCTBConverter(com.sun.corba.se.impl.encoding.OSFCodeSetRegistry.Entry, boolean, boolean)'>
        <annotation name='org.jetbrains.annotations.NotNull'/>
    </item>
    <item name='com.sun.corba.se.impl.encoding.CodeSetConversion com.sun.corba.se.impl.encoding.CodeSetComponentInfo.CodeSetContext negotiate(com.sun.corba.se.impl.encoding.CodeSetComponentInfo, com.sun.corba.se.impl.encoding.CodeSetComponentInfo)'>
        <annotation name='org.jetbrains.annotations.NotNull'/>
    </item>
    <item name='com.sun.corba.se.impl.encoding.EncapsInputStream com.sun.corba.se.impl.encoding.CodeSetConversion.BTCConverter createCharBTCConverter()'>
        <annotation name='org.jetbrains.annotations.NotNull'/>
    </item>
    <item name='com.sun.corba.se.impl.encoding.EncapsInputStream com.sun.corba.se.impl.encoding.CodeSetConversion.BTCConverter createWCharBTCConverter()'>
        <annotation name='org.jetbrains.annotations.NotNull'/>
    </item>
    <item name='com.sun.corba.se.impl.encoding.EncapsInputStream com.sun.corba.se.impl.encoding.CDRInputStream dup()'>
        <annotation name='org.jetbrains.annotations.NotNull'/>
    </item>
    <item name='com.sun.corba.se.impl.encoding.EncapsOutputStream com.sun.corba.se.impl.encoding.CodeSetConversion.CTBConverter createCharCTBConverter()'>
        <annotation name='org.jetbrains.annotations.NotNull'/>
    </item>
    <item name='com.sun.corba.se.impl.encoding.EncapsOutputStream com.sun.corba.se.impl.encoding.CodeSetConversion.CTBConverter createWCharCTBConverter()'>
        <annotation name='org.jetbrains.annotations.NotNull'/>
    </item>
    <item name='com.sun.corba.se.impl.encoding.EncapsOutputStream org.omg.CORBA.portable.InputStream create_input_stream()'>
        <annotation name='org.jetbrains.annotations.NotNull'/>
    </item>
    <item name='com.sun.corba.se.impl.encoding.IDLJavaSerializationInputStream com.sun.corba.se.impl.encoding.CDRInputStreamBase dup()'>
        <annotation name='org.jetbrains.annotations.NotNull'/>
    </item>
    <item name='com.sun.corba.se.impl.encoding.IDLJavaSerializationInputStream org.omg.CORBA.Principal read_Principal()'>
        <annotation name='org.jetbrains.annotations.NotNull'/>
    </item>
    <item name='com.sun.corba.se.impl.encoding.IDLJavaSerializationInputStream org.omg.CORBA.TypeCode read_TypeCode()'>
        <annotation name='org.jetbrains.annotations.NotNull'/>
    </item>
    <item name='com.sun.corba.se.impl.encoding.IDLJavaSerializationInputStream org.omg.CORBA.Any read_any()'>
        <annotation name='org.jetbrains.annotations.NotNull'/>
    </item>
    <item name='com.sun.corba.se.impl.encoding.IDLJavaSerializationInputStream java.math.BigDecimal read_fixed()'>
        <annotation name='org.jetbrains.annotations.NotNull'/>
    </item>
    <item name='com.sun.corba.se.impl.encoding.IDLJavaSerializationInputStream java.math.BigDecimal read_fixed(short, short)'>
        <annotation name='org.jetbrains.annotations.NotNull'/>
    </item>
    <item name='com.sun.corba.se.impl.encoding.IDLJavaSerializationInputStream java.lang.StringBuffer read_fixed_buffer()'>
        <annotation name='org.jetbrains.annotations.NotNull'/>
    </item>
    <item name='com.sun.corba.se.impl.encoding.IDLJavaSerializationOutputStream com.sun.corba.se.impl.encoding.ByteBufferWithInfo getByteBufferWithInfo()'>
        <annotation name='org.jetbrains.annotations.NotNull'/>
    </item>
    <item name='com.sun.corba.se.impl.encoding.OSFCodeSetRegistry ISO_646'>
        <annotation name='org.jetbrains.annotations.NotNull'/>
    </item>
    <item name='com.sun.corba.se.impl.encoding.OSFCodeSetRegistry ISO_8859_1'>
        <annotation name='org.jetbrains.annotations.NotNull'/>
    </item>
    <item name='com.sun.corba.se.impl.encoding.OSFCodeSetRegistry UCS_2'>
        <annotation name='org.jetbrains.annotations.NotNull'/>
    </item>
    <item name='com.sun.corba.se.impl.encoding.OSFCodeSetRegistry UTF_16'>
        <annotation name='org.jetbrains.annotations.NotNull'/>
    </item>
    <item name='com.sun.corba.se.impl.encoding.OSFCodeSetRegistry UTF_16BE'>
        <annotation name='org.jetbrains.annotations.NotNull'/>
    </item>
    <item name='com.sun.corba.se.impl.encoding.OSFCodeSetRegistry UTF_16LE'>
        <annotation name='org.jetbrains.annotations.NotNull'/>
    </item>
    <item name='com.sun.corba.se.impl.encoding.OSFCodeSetRegistry UTF_8'>
        <annotation name='org.jetbrains.annotations.NotNull'/>
    </item>
    <item name='com.sun.corba.se.impl.encoding.TypeCodeInputStream com.sun.corba.se.impl.encoding.TypeCodeInputStream readEncapsulation(org.omg.CORBA_2_3.portable.InputStream, org.omg.CORBA.ORB)'>
        <annotation name='org.jetbrains.annotations.NotNull'/>
    </item>
    <item name='com.sun.corba.se.impl.encoding.TypeCodeOutputStream com.sun.corba.se.impl.encoding.TypeCodeOutputStream createEncapsulation(org.omg.CORBA.ORB)'>
        <annotation name='org.jetbrains.annotations.NotNull'/>
    </item>
    <item name='com.sun.corba.se.impl.encoding.TypeCodeOutputStream org.omg.CORBA.portable.InputStream create_input_stream()'>
        <annotation name='org.jetbrains.annotations.NotNull'/>
    </item>
    <item name='com.sun.corba.se.impl.encoding.TypeCodeOutputStream byte[] getTypeCodeBuffer()'>
        <annotation name='org.jetbrains.annotations.NotNull'/>
    </item>
    <item name='com.sun.corba.se.impl.encoding.TypeCodeOutputStream com.sun.corba.se.impl.encoding.TypeCodeOutputStream wrapOutputStream(org.omg.CORBA_2_3.portable.OutputStream)'>
        <annotation name='org.jetbrains.annotations.NotNull'/>
    </item>
    <item name='com.sun.corba.se.impl.encoding.WrapperInputStream com.sun.corba.se.impl.encoding.TypeCodeReader getTopLevelStream()'>
        <annotation name='org.jetbrains.annotations.NotNull'/>
    </item>
</root>
